{
  "name" : "变异枝条",
  "icon" : "witchery:mutating_sprig",
  "category" : "witchery",
  "sortnum" : 6,
  "pages": [
    {
      "type" : "text",
      "text" : "变异枝条是用巫师炼药锅制作的道具，主要作用其实是变异生物，通过变异枝条变异才能获得的动植物和道具一览：$(br)擒拿草，生物陷阱，血玫瑰，水蛭箱子，苦艾，寄生虱，矿德拉草，猫头鹰，蟾蜍，飞天猴子，虚空荆棘，末影荆棘，野荆棘。$(br)下面我们来一一介绍这些动植物和道具的获得方式和用途。"
    },
    {
      "type" : "spotlight",
      "item" : "witchery:grassper",
      "text" : "擒拿草的功能是可以放置一个道具的植物。该植物属于其他变异需求的基本植物，而且携带道具的擒拿草可以用来为圆环法阵提供材料，怕丢地上消失的玩家可以选择在法阵中放置擒拿草并把道具摆在上面来激活法阵。"
    },
    {
      "type": "image",
      "images": [
        "patchouli:entries/witchery/witchery1.png"
      ]
    },
    {
      "type" : "text",
      "text": "在静止的水上放置一个箱子，箱子四周放上草（用剪刀打草来收集），然后用变异枝条右键箱子，然后箱子会消失，四周的四个草就变成擒拿草了。空手破坏即可获取。"
    },
    {
      "type" : "spotlight",
      "item" : "witchery:empty_critter_snare",
      "text" : "生物陷阱是用来捕捉小型生物的道具植物，该陷阱可以捕捉的生物非常有限：蝙蝠，小史莱姆，蠢虫，小岩浆怪。该植物放置在地面上后，可以捕捉的生物靠近后就会被抓起来，一个陷阱只能捕捉一个。需要用伯莱恩匕首收获才能得到带有生物的生物陷阱。"
    },
    {
      "type": "image",
      "images": [
        "patchouli:entries/witchery/witchery2.png"
      ]
    },
    {
      "type" : "text",
      "text": "在静止的水上方放置一个蜘蛛网，蜘蛛网四周摆放4个赤杨树树苗，然后蜘蛛网内需要有一只僵尸，然后用变异枝条右键蜘蛛网。"
    },
    {
      "type" : "spotlight",
      "item" : "witchery:blood_poppy",
      "text" : "血玫瑰可以在任何方块表面放置，不需要非得是草地或者泥土。该作物的作用主要是获取巫媒，可以保存上一个经过该植物的生物的巫媒，用未绑定的巫媒右键血玫瑰可以获取，该保存只能获得一次，再次获得需要再次经过。"
    },
    {
      "type": "image",
      "images": [
        "patchouli:entries/witchery/witchery3.png"
      ]
    },
    {
      "type" : "text",
      "text": "静止的水上方放置一个水蛭箱子，水蛭箱子四周放置一个罂粟（此处官方的说明是玫瑰丛，亲测需要罂粟）。然后用变异枝条右键水蛭箱子。"
    },
    {
      "type" : "spotlight",
      "item" : "witchery:leech_chest",
      "text" : "该箱子可以记录最多3个使用过他的玩家的巫媒，获取记录的巫媒需要用未绑定的巫媒右键箱子上面的3个红点。这个记录是维持最后三名使用它的玩家，巫媒获取这不能获得自己的巫媒。获取别人的巫媒需要对方在这个世界中。破坏并再次放置巫媒记录不会消失。"
    },
    {
      "type": "image",
      "images": [
        "patchouli:entries/witchery/witchery4.png"
      ]
    },
    {
      "type" : "text",
      "text": "地面上放置一个陷阱箱（注意不是普通箱子），箱子四周是一格的静止水，箱子四面水上的1格要各放置一个藤蔓。然后用变异枝条右键陷阱箱。"
    },
    {
      "type" : "spotlight",
      "item" : "witchery:wormwood",
      "text" : "该植物的主要作用是用来用火盆召唤幽灵生物，种植在耕地上，最多可以生长2格高（每格分开计算成熟和收获）。该植物需要纤细棉花，而且召唤幽灵生物制作灵物属于巫术mod的顶级科技，前期不推荐制作。"
    },


    {
      "type": "image",
      "images": [
        "patchouli:entries/witchery/witchery5.png"
      ]
    },
    {
      "type" : "text",
      "text": "耕地上种植出完全成熟的小麦，小麦四周放置纤细棉花，小麦的四个角放置1格的静止水，然后用变异枝条右键小麦。"
    },
    {
      "type" : "spotlight",
      "item" : "witchery:parasytic_louse",
      "text" : "主要用途是用来制作巫术的顶级防具树人腰带，树皮护甲制作的必要材料。本身也可以与喷溅类药水在工作台合成，合成后放在快捷栏时，被攻击会把有益的药水对自己使用，有害的药水对攻击者使用，快捷栏最多同时只能触发一条寄生虱的效果。作为道具形态右键地面可以召唤，生物形态右键互动会变成道具。"
    },


    {
      "type": "image",
      "images": [
        "patchouli:entries/witchery/witchery6.png"
      ]
    },
    {
      "type": "text",
      "text": "地面上放置一个捕获了蠢虫的生物陷阱，生物陷阱四周是一格的静止水，水上放置睡莲。生物陷阱的四个角放置四个擒拿草，擒拿草上放置1个调谐之石（充能），1个狗之舌，和2个转生粉。摆放完成后用变异枝条右键擒拿草，就会出现一个生物形态的敌对寄生虱。"
    },
    {
      "type" : "spotlight",
      "item" : "witchery:mindrake_bulb",
      "text" : "先说好这是所有变异生物中最难最难制作的一个，用于巫师炼药锅的酿造系统中延长药效的持续时间。"
    },


    {
      "type": "image",
      "images": [
        "patchouli:entries/witchery/witchery7.png"
      ]
    },
    {
      "type": "text",
      "text": "一格静止水上方放置一个蜘蛛网，蜘蛛网四周上在耕地上种植出成熟的曼德拉草，蜘蛛网四角放置四个擒拿草，擒拿草放置1个调谐之石（充能），2个超级转生粉和1个汇聚之意志（蒸馏塔），蜘蛛网中需要有一个曼德拉草生物和一个爬行者。用变异枝条右键蜘蛛网，你就获得了四个矿德拉草。"
    },
    {
      "type" : "entity",
      "entity" : "witchery:owl",
      "text" : "用生猪排或者生牛排喂养可以驯服,满足条件可以繁殖。击杀概率掉落小猫头鹰之翼。"
    },
    {
      "type": "image",
      "images": [
        "patchouli:entries/witchery/witchery8.png"
      ]
    },
    {
      "type": "text",
      "text": "静止水上方放置一个蜘蛛网，蜘蛛网四周是2-4个带蝙蝠的生物陷阱（这个数目决定了产生猫头鹰的数量，4个就是4个猫头鹰），蜘蛛网四角放置四个擒拿草，擒拿草上放置1个调谐之石（充能）和三个超级转生粉，蜘蛛网内有一只狼或者狗或者愤怒的狼，然后用变异枝条右键蜘蛛网。"
    },
    {
      "type" : "entity",
      "entity" : "witchery:toad",
      "text" : "该生物被击杀概率掉落青蛙趾和粘液球，可以用腐肉驯服，满足条件可以繁殖。"
    },
    {
      "type": "image",
      "images": [
        "patchouli:entries/witchery/witchery9.png"
      ]
    },
    {
      "type": "text",
      "text": "静止水上方放置一个蜘蛛网，蜘蛛网四周是捕获了小史莱姆的生物陷阱（这个数目决定了蟾蜍的数量，4个就是4只蟾蜍），蜘蛛网四个角放置四个擒拿草，擒拿草上放置1个调谐之石（充能）和三个超级转生粉，蜘蛛网内有一只猫或者豹猫，准备就绪后用变异枝条右键蜘蛛网。"
    },
    {
      "type" : "entity",
      "entity" : "witchery:winged_monkey",
      "text" : "可以用生猪排或者生牛排驯服。"
    },
    {
      "type": "image",
      "images": [
        "patchouli:entries/witchery/witchery10.png"
      ]
    },
    {
      "type": "text",
      "text": "静止水上方放置一个蜘蛛网，蜘蛛网四周是成熟的可可豆（需要在从林木上种植），蜘蛛网四角放置四个擒拿草，擒拿草上放置一个调谐之石（充能），2个超级转生粉和1个罂粟，蜘蛛网内有一只猫头鹰和一只狗，准备好后用变异枝条右键蜘蛛网。$(br) 给它巫媒他会寻找到巫媒对象并携带其回到主人身边，给它绑定的寻路石或者血腥路碑他会把主人带到寻路石的位置，寻路石不会被消耗然而巫媒会被消耗。"
    },
    {
      "type" : "spotlight",
      "item" : "witchery:ender_bramble",
      "text" : "所有靠近的生物都会被传送到500范围内，然而除了这点他就没啥特别的了....注意中立生物甚至敌对生物也会被传送，放置前请三思。"
    },


    {
      "type": "image",
      "images": [
        "patchouli:entries/witchery/witchery11.png"
      ]
    },
    {
      "type": "text",
      "text": "平地上放置甘蔗，甘蔗四周是静止水，甘蔗四个角放置擒拿草，擒拿草上放置四个末影珍珠，两个擒拿草之前的那个方块要放置一个寄生藤，准备好了后用变异枝条右键最下面的那个甘蔗方块，最多可以累积16个甘蔗高来一次制作16个末影荆棘。记得用剪刀采集或者用水冲。"
    },
    {
      "type" : "spotlight",
      "item" : "witchery:wild_bramble",
      "text" : "野荆棘和仙人掌一样会对碰到的生物造成伤害。野荆棘只能用金斧破坏或者用其他特殊破坏手段（破坏根部的泥土方块或者用水冲）来清除，正常斧头等方式破坏会产生更多的野荆棘。"
    },


    {
      "type": "image",
      "images": [
        "patchouli:entries/witchery/witchery12.png"
      ]
    },
    {
      "type": "text",
      "text": "沙子上放置仙人掌，仙人掌四周是静止水，仙人掌四角放置4个擒拿草，擒拿草上放置2个骨粉和两个烈焰粉，放置顺序无所谓。仙人掌最多16格高。擒拿草中间的方块放置一个寄生藤，准备好后用变异枝条右键最下面的仙人掌方块。"
    }
  ]
}
